tli
