Metadata-Version: 1.1
Name: tli
Version: 2.1
Summary: A Twitter (command) Line Interface
Home-page: https://github.com/leonjza/tli
Author: Leon Jacobs
Author-email: leonja511@gmail.com
License: UNKNOWN
Download-URL: https://github.com/leonjza/tli/tarball/2.1
Keywords: twitter,line,console,command,client
Platform: UNKNOWN
